geoipapi/__init__.py
geoipapi/_hooks/__init__.py
geoipapi/_hooks/registration.py
geoipapi/_hooks/sdkhooks.py
geoipapi/_hooks/types.py
geoipapi/_version.py
geoipapi/basesdk.py
geoipapi/errors/__init__.py
geoipapi/errors/apierror.py
geoipapi/errors/httpvalidationerror.py
geoipapi/geoip_endpoints.py
geoipapi/httpclient.py
geoipapi/models/__init__.py
geoipapi/models/asninfo.py
geoipapi/models/countryinfo.py
geoipapi/models/errorresponse.py
geoipapi/models/geoipresponse.py
geoipapi/models/get_ip_dataop.py
geoipapi/models/locationinfo.py
geoipapi/models/validationerror.py
geoipapi/py.typed
geoipapi/sdk.py
geoipapi/sdkconfiguration.py
geoipapi/types/__init__.py
geoipapi/types/basemodel.py
geoipapi/utils/__init__.py
geoipapi/utils/annotations.py
geoipapi/utils/datetimes.py
geoipapi/utils/enums.py
geoipapi/utils/eventstreaming.py
geoipapi/utils/forms.py
geoipapi/utils/headers.py
geoipapi/utils/logger.py
geoipapi/utils/metadata.py
geoipapi/utils/queryparams.py
geoipapi/utils/requestbodies.py
geoipapi/utils/retries.py
geoipapi/utils/security.py
geoipapi/utils/serializers.py
geoipapi/utils/url.py
geoipapi/utils/values.py
geoipapi-0.0.1.dist-info/METADATA
geoipapi-0.0.1.dist-info/WHEEL
geoipapi-0.0.1.dist-info/RECORD
