Metadata-Version: 2.3
Name: geoipapi
Version: 0.0.1
Summary: Python Client SDK Generated by Speakeasy.
Author: Speakeasy
Requires-Python: >=3.9.2
Classifier: Programming Language :: Python :: 3
Classifier: Programming Language :: Python :: 3.10
Classifier: Programming Language :: Python :: 3.11
Classifier: Programming Language :: Python :: 3.12
Classifier: Programming Language :: Python :: 3.13
Requires-Dist: httpcore (>=1.0.9)
Requires-Dist: httpx (>=0.28.1)
Requires-Dist: pydantic (>=2.11.2)
